[
  {
    "id": "arb_camelot",
    "chain": "arb",
    "name": "Camelot",
    "site_url": "https://app.camelot.exchange",
    "logo_url": "https://static.debank.com/image/project/logo_url/arb_camelot/e5ba705c36ff1c84559cc8c82e540acd.png",
    "has_supported_portfolio": true,
    "tvl": 45891745.39188349,
    "net_usd_value": 254.8555983713681,
    "asset_usd_value": 254.8555983713681,
    "debt_usd_value": 0
  },
  {
    "id": "arb_superfluid",
    "chain": "arb",
    "name": "Superfluid",
    "site_url": "https://app.superfluid.finance",
    "logo_url": "https://static.debank.com/image/project/logo_url/arb_superfluid/b44e6c22d10a555798f43cf205e50a59.png",
    "has_supported_portfolio": true,
    "tvl": 128047.76738889478,
    "net_usd_value": 0.3050994495623369,
    "asset_usd_value": 0.3050994495623369,
    "debt_usd_value": 0
  },
  {
    "id": "arb_sushiswap",
    "chain": "arb",
    "name": "SushiSwap",
    "site_url": "https://www.sushi.com/swap",
    "logo_url": "https://static.debank.com/image/project/logo_url/arb_sushiswap/b3fb55a581caeb78263c8e192b9aa141.png",
    "has_supported_portfolio": true,
    "tvl": 46509356.80600067,
    "net_usd_value": 7.354654164338827,
    "asset_usd_value": 7.354654164338827,
    "debt_usd_value": 0
  },
  {
    "id": "avax_stargate",
    "chain": "avax",
    "name": "Stargate",
    "site_url": "https://stargate.finance",
    "logo_url": "https://static.debank.com/image/project/logo_url/stargate/3c6fbbbb1e62793ee34effb91d8769e7.png",
    "has_supported_portfolio": true,
    "tvl": 22443720.870734747,
    "net_usd_value": 2.1047017858528294,
    "asset_usd_value": 2.1047017858528294,
    "debt_usd_value": 0
  },
  {
    "id": "base_teahouse",
    "chain": "base",
    "name": "Teahouse",
    "site_url": "https://vault.teahouse.finance",
    "logo_url": "https://static.debank.com/image/project/logo_url/teahouse/ea1e557999196333ea84ad87e6e9024b.png",
    "has_supported_portfolio": true,
    "tvl": 73675.28142373159,
    "net_usd_value": 3.0153470316902005,
    "asset_usd_value": 3.0153470316902005,
    "debt_usd_value": 0
  },
  {
    "id": "bsc_pancakeswap3",
    "chain": "bsc",
    "name": "PancakeSwap V3",
    "site_url": "https://pancakeswap.finance",
    "logo_url": "https://static.debank.com/image/project/logo_url/bsc_pancakeswap3/d575f1697e05d43c237e3986dae3e8bb.png",
    "has_supported_portfolio": true,
    "tvl": 456978942.1527734,
    "net_usd_value": 229.55555070730318,
    "asset_usd_value": 229.55555070730318,
    "debt_usd_value": 0
  },
  {
    "id": "bsc_xen",
    "chain": "bsc",
    "name": "Xen",
    "site_url": "https://xen.network/",
    "logo_url": "https://static.debank.com/image/project/logo_url/bsc_xen/542623eaf7b87ab6f39b486e4cb7fdb8.png",
    "has_supported_portfolio": true,
    "tvl": 10058.720000127201,
    "net_usd_value": 0.00022304389417323247,
    "asset_usd_value": 0.00022304389417323247,
    "debt_usd_value": 0
  },
  {
    "id": "dydx",
    "chain": "eth",
    "name": "dYdX",
    "site_url": "https://trade.dydx.exchange",
    "logo_url": "https://static.debank.com/image/project/logo_url/dydx/5f1976abb3702eddecb978580abed8d8.png",
    "has_supported_portfolio": true,
    "tvl": 11640249.199270066,
    "net_usd_value": 0.6487001625680029,
    "asset_usd_value": 0.6487001625680029,
    "debt_usd_value": 0
  },
  {
    "id": "kroma_izumi",
    "chain": "kroma",
    "name": "iZUMi Finance",
    "site_url": "https://izumi.finance",
    "logo_url": "https://static.debank.com/image/project/logo_url/era_izumi/b85326453b2e2b60652343c9b7fd729e.png",
    "has_supported_portfolio": true,
    "tvl": 990028.6597104305,
    "net_usd_value": 4.256928334988695,
    "asset_usd_value": 4.256928334988695,
    "debt_usd_value": 0
  },
  {
    "id": "linea_lynex",
    "chain": "linea",
    "name": "Lynex",
    "site_url": "https://app.lynex.fi",
    "logo_url": "https://static.debank.com/image/project/logo_url/linea_lynex/a7c591c4cd2be908e52f6c70d168824f.png",
    "has_supported_portfolio": true,
    "tvl": 29706638.278556254,
    "net_usd_value": 15.854716675234627,
    "asset_usd_value": 15.854716675234627,
    "debt_usd_value": 0
  },
  {
    "id": "linea_secta",
    "chain": "linea",
    "name": "Secta",
    "site_url": "https://www.secta.finance",
    "logo_url": "https://static.debank.com/image/project/logo_url/linea_secta/f3db22fa0978790d40ae06a0f762a7cc.png",
    "has_supported_portfolio": true,
    "tvl": 300148.36785967747,
    "net_usd_value": 7.833151064715802,
    "asset_usd_value": 7.833151064715802,
    "debt_usd_value": 0
  },
  {
    "id": "linea_syncswap",
    "chain": "linea",
    "name": "SyncSwap",
    "site_url": "https://syncswap.xyz",
    "logo_url": "https://static.debank.com/image/project/logo_url/era_syncswap/ee418f0e253f581088c7cfbe7b40760f.png",
    "has_supported_portfolio": true,
    "tvl": 23234284.844887633,
    "net_usd_value": 0.007088987555924698,
    "asset_usd_value": 0.007088987555924698,
    "debt_usd_value": 0
  },
  {
    "id": "linea_teahouse",
    "chain": "linea",
    "name": "Teahouse",
    "site_url": "https://vault.teahouse.finance",
    "logo_url": "https://static.debank.com/image/project/logo_url/teahouse/ea1e557999196333ea84ad87e6e9024b.png",
    "has_supported_portfolio": true,
    "tvl": 1868704.0600100153,
    "net_usd_value": 3.5532197251314512,
    "asset_usd_value": 3.5532197251314512,
    "debt_usd_value": 0
  },
  {
    "id": "linea_visor",
    "chain": "linea",
    "name": "Gamma",
    "site_url": "https://v2.gamma.xyz/",
    "logo_url": "https://static.debank.com/image/project/logo_url/matic_visor/a3ed8f14e6af316ac4fa68bd9a364cf9.png",
    "has_supported_portfolio": true,
    "tvl": 11413072.47046014,
    "net_usd_value": 51.755592696937754,
    "asset_usd_value": 51.755592696937754,
    "debt_usd_value": 0
  },
  {
    "id": "matic_uniswap3",
    "chain": "matic",
    "name": "Uniswap V3",
    "site_url": "https://app.uniswap.org",
    "logo_url": "https://static.debank.com/image/project/logo_url/uniswap3/87a541b3b83b041c8d12119e5a0d19f0.png",
    "has_supported_portfolio": true,
    "tvl": 493276213.03286356,
    "net_usd_value": 136.77076733361676,
    "asset_usd_value": 136.77076733361676,
    "debt_usd_value": 0
  },
  {
    "id": "mode_kim",
    "chain": "mode",
    "name": "Kim",
    "site_url": "https://app.kim.exchange",
    "logo_url": "https://static.debank.com/image/project/logo_url/mode_kim/19c545c9df24e510055a2088ea0f611d.png",
    "has_supported_portfolio": true,
    "tvl": 10404640.379113737,
    "net_usd_value": 4.4227510728333606,
    "asset_usd_value": 4.4227510728333606,
    "debt_usd_value": 0
  },
  {
    "id": "pls_hedronswap",
    "chain": "pls",
    "name": "Hedron Swap",
    "site_url": "https://swap.hedron.pro/#/swap",
    "logo_url": "https://static.debank.com/image/project/logo_url/pls_hedronswap/b6ada9ff0ccd6604fa9fbcd567f49dd4.png",
    "has_supported_portfolio": true,
    "tvl": 329935.4655754066,
    "net_usd_value": 0.1256233571390863,
    "asset_usd_value": 0.1256233571390863,
    "debt_usd_value": 0
  },
  {
    "id": "pls_pulsex",
    "chain": "pls",
    "name": "PulseX",
    "site_url": "https://app.pulsex.com",
    "logo_url": "https://static.debank.com/image/project/logo_url/pls_pulsex/66c1e80d2ab71189593c58ad5f7620d5.png",
    "has_supported_portfolio": true,
    "tvl": 219979999.77180925,
    "net_usd_value": 268.31695474236665,
    "asset_usd_value": 268.31695474236665,
    "debt_usd_value": 0
  },
  {
    "id": "pls_xen",
    "chain": "pls",
    "name": "Xen",
    "site_url": "https://xen.network",
    "logo_url": "https://static.debank.com/image/project/logo_url/avax_xen/542623eaf7b87ab6f39b486e4cb7fdb8.png",
    "has_supported_portfolio": true,
    "tvl": 2740.8898292525673,
    "net_usd_value": 0.0000818573967698677,
    "asset_usd_value": 0.0000818573967698677,
    "debt_usd_value": 0
  },
  {
    "id": "scrl_ambient",
    "chain": "scrl",
    "name": "Ambient",
    "site_url": "https://ambient.finance",
    "logo_url": "https://static.debank.com/image/project/logo_url/ambient/c3a293380b2dd3aee35f0e8ac9bee9bc.png",
    "has_supported_portfolio": true,
    "tvl": 80599037.41090813,
    "net_usd_value": 2.08555696162006,
    "asset_usd_value": 2.08555696162006,
    "debt_usd_value": 0
  },
  {
    "id": "scrl_syncswap",
    "chain": "scrl",
    "name": "SyncSwap",
    "site_url": "https://syncswap.xyz",
    "logo_url": "https://static.debank.com/image/project/logo_url/era_syncswap/ee418f0e253f581088c7cfbe7b40760f.png",
    "has_supported_portfolio": true,
    "tvl": 15253820.689450637,
    "net_usd_value": 3.0941372069741924,
    "asset_usd_value": 3.0941372069741924,
    "debt_usd_value": 0
  },
  {
    "id": "scrl_teahouse",
    "chain": "scrl",
    "name": "Teahouse",
    "site_url": "https://vault.teahouse.finance",
    "logo_url": "https://static.debank.com/image/project/logo_url/teahouse/ea1e557999196333ea84ad87e6e9024b.png",
    "has_supported_portfolio": true,
    "tvl": 48827.365551122224,
    "net_usd_value": 5.318758358810449,
    "asset_usd_value": 5.318758358810449,
    "debt_usd_value": 0
  },
  {
    "id": "taiko_ritsu",
    "chain": "taiko",
    "name": "Ritsu",
    "site_url": "https://ritsu.xyz",
    "logo_url": "https://static.debank.com/image/project/logo_url/taiko_ritsu/8a4bdd6bd8250e057743eff95dccdf50.png",
    "has_supported_portfolio": true,
    "tvl": 634414.5596212785,
    "net_usd_value": 16.235936393454416,
    "asset_usd_value": 16.235936393454416,
    "debt_usd_value": 0
  },
  {
    "id": "tokensets",
    "chain": "eth",
    "name": "TokenSets",
    "site_url": "https://tokensets.com",
    "logo_url": "https://static.debank.com/image/project/logo_url/tokensets/b6ed6c4eb80b279ceaf2c768fbbb3c8d.png",
    "has_supported_portfolio": true,
    "tvl": 64696804.93294688,
    "net_usd_value": 33.04541651812662,
    "asset_usd_value": 33.04541651812662,
    "debt_usd_value": 0
  },
  {
    "id": "uniswap2",
    "chain": "eth",
    "name": "Uniswap V2",
    "site_url": "https://app.uniswap.org",
    "logo_url": "https://static.debank.com/image/project/logo_url/uniswap2/87a541b3b83b041c8d12119e5a0d19f0.png",
    "has_supported_portfolio": true,
    "tvl": 1164127439.5709605,
    "net_usd_value": 8.702570532319534,
    "asset_usd_value": 8.702570532319534,
    "debt_usd_value": 0
  },
  {
    "id": "uniswap3",
    "chain": "eth",
    "name": "Uniswap V3",
    "site_url": "https://app.uniswap.org",
    "logo_url": "https://static.debank.com/image/project/logo_url/uniswap3/87a541b3b83b041c8d12119e5a0d19f0.png",
    "has_supported_portfolio": true,
    "tvl": 2121144615.223484,
    "net_usd_value": 522.2268724286988,
    "asset_usd_value": 522.2268724286988,
    "debt_usd_value": 0
  },
  {
    "id": "xen",
    "chain": "eth",
    "name": "Xen",
    "site_url": "https://xen.network/",
    "logo_url": "https://static.debank.com/image/project/logo_url/xen/542623eaf7b87ab6f39b486e4cb7fdb8.png",
    "has_supported_portfolio": true,
    "tvl": 353065.33296098886,
    "net_usd_value": 0.024722694420059848,
    "asset_usd_value": 0.024722694420059848,
    "debt_usd_value": 0
  },
  {
    "id": "zkfair_sideswap",
    "chain": "zkfair",
    "name": "Sideswap",
    "site_url": "https://sideswap.finance",
    "logo_url": "https://static.debank.com/image/project/logo_url/zkfair_sideswap/e5f90c985d096de82b501501ee1b0c46.png",
    "has_supported_portfolio": true,
    "tvl": 85580.90550007115,
    "net_usd_value": 23.422406719955994,
    "asset_usd_value": 23.422406719955994,
    "debt_usd_value": 0
  }
]